okazaki/__init__.py
okazaki/helpers.py
okazaki/ai/__init__.py
okazaki/ai/labeler.py
okazaki/ai/langchain.py
okazaki/ai/summarize.py
okazaki/ai/tyran.py
okazaki/api/__init__.py
okazaki/api/app.py
okazaki/api/client.py
okazaki/api/issue.py
okazaki/api/label.py
okazaki/api/milestone.py
okazaki/api/pull_request.py
okazaki/api/repository.py
okazaki/api/statistics.py
okazaki/api/webhook.py
okazaki/config/__init__.py
okazaki/config/config_parser.py
okazaki/config/local_config_reader.py
okazaki/config/remote_config_reader.py
okazaki/exception/__init__.py
okazaki/exception/api_error.py
okazaki/exception/not_found.py
okazaki/plugins/__init__.py
okazaki/plugins/auto_triage_v1.py
okazaki/plugins/labels_v1.py
okazaki/plugins/stale_v1.py
okazaki/util/__init__.py
okazaki/util/file_system.py
okazaki/util/logger.py
okazaki-0.4.20.dist-info/LICENSE.txt
okazaki-0.4.20.dist-info/METADATA
okazaki-0.4.20.dist-info/WHEEL
okazaki-0.4.20.dist-info/top_level.txt
okazaki-0.4.20.dist-info/RECORD
