Metadata-Version: 2.1
Name: okazaki
Version: 0.4.20
Summary: Github Automation Package in Python Powered By AI
Home-page: https://github.com/clivern/okazaki/
Author: Clivern
Author-email: hello@clivern.com
License: MIT
Project-URL: Documentation, https://github.com/clivern/okazaki/
Project-URL: Source, https://github.com/clivern/okazaki/
Project-URL: Changelog, https://github.com/clivern/okazaki/blob/main/CHANGELOG.rst
Project-URL: Tracker, https://github.com/clivern/okazaki/issues
Project-URL: Download, https://pypi.org/project/okazaki/#files
Platform: any
Classifier: Development Status :: 5 - Production/Stable
Classifier: Programming Language :: Python
Classifier: License :: OSI Approved :: MIT License
License-File: LICENSE.txt
Requires-Dist: PyGithub<=2.5.0
Requires-Dist: langchain<=0.3.12
Requires-Dist: langchain-openai<=0.2.12
Requires-Dist: pyjwt<=2.10.1
Requires-Dist: cryptography<=44.0.0
Requires-Dist: pycryptodome<=3.21.0
Requires-Dist: python-dateutil<=2.9.0.post0
Requires-Dist: pyyaml<=6.0.2
Requires-Dist: openai<=1.57.4
Requires-Dist: requests<=2.32.3
Requires-Dist: importlib-metadata; python_version < "3.8"
